semantic_diffs/__init__.py
semantic_diffs/action.py
semantic_diffs/nodes.py
semantic_diffs/py.typed
semantic_diffs-0.0.0.dist-info/LICENSE
semantic_diffs-0.0.0.dist-info/METADATA
semantic_diffs-0.0.0.dist-info/WHEEL
semantic_diffs-0.0.0.dist-info/RECORD
