Metadata-Version: 2.1
Name: semantic_diffs
Version: 0.0.0
Summary: Reuse codebase changes to automate refactoring.
Home-page: https://github.com/bswck/semantic_diffs
License: MIT
Author: bswck
Author-email: bswck.dev@gmail.com
Requires-Python: >=3.8,<4.0
Classifier: License :: OSI Approved :: MIT License
Classifier: Programming Language :: Python :: 3
Classifier: Programming Language :: Python :: 3.8
Classifier: Programming Language :: Python :: 3.9
Classifier: Programming Language :: Python :: 3.10
Classifier: Programming Language :: Python :: 3.11
Classifier: Programming Language :: Python :: 3.12
Project-URL: Coverage, https://coverage-badge.samuelcolvin.workers.dev/redirect/bswck/semantic_diffs
Project-URL: Documentation, https://semantic-diffs.readthedocs.io/en/latest/
Project-URL: Distribution, https://pypi.org/project/semantic-diffs/
Project-URL: Issues, https://github.com/bswck/semantic_diffs/issues
